{"name":"Global Apartments","centerCoordinates":{"lat":50.2623116,"lng":19.0132716},"locations":[{"name":"Mieszkanie","coordinates":{"lat":50.2623116,"lng":19.0132716}},{"name":"Biedronka-3.7⭐️","coordinates":{"lat":50.2620136,"lng":19.0260513}},{"name":"Netto-4⭐️","coordinates":{"lat":50.263726,"lng":19.0045847}},{"name":"Biedronka-4⭐️","coordinates":{"lat":50.2659452,"lng":18.9973311}},{"name":"Biedronka-4.1⭐️","coordinates":{"lat":50.26288539999999,"lng":19.0108347}},{"name":"ALDI-4.1⭐️","coordinates":{"lat":50.26214839999999,"lng":19.0189567}},{"name":"Park-4.7⭐️","coordinates":{"lat":50.2557431,"lng":19.0146782}},{"name":"Kosciuszko Park-4.6⭐️","coordinates":{"lat":50.2459046,"lng":19.0046438}},{"name":"Park Wełnowiecki w Katowicach-4.5⭐️","coordinates":{"lat":50.2787599,"lng":19.0282729}},{"name":"Academy of Yoga & Movement Therapy-4.7⭐️","coordinates":{"lat":50.2633365,"lng":19.0138903}},{"name":"Trening EMS - BodyTec20+ Opolska-4.6⭐️","coordinates":{"lat":50.2621648,"lng":19.0115511}},{"name":"Savitri Yoga Harmonia Duszy i Ciała - Szkoła Jogi - Joga Katowice-4.9⭐️","coordinates":{"lat":50.2604548,"lng":19.0133715}},{"name":"протестантская церковь для русскоговорящих-⭐️","coordinates":{"lat":50.26349439999999,"lng":19.0135333}},{"name":"Wspólnota Dobrego Pasterza-3.9⭐️","coordinates":{"lat":50.26122760000001,"lng":19.0143139}},{"name":"Kościół rzymskokatolicki pw. Przemienienia Pańskiego w Katowicach-4.4⭐️","coordinates":{"lat":50.2621925,"lng":19.0154654}},{"name":"Katowice Plac Wolności-4⭐️","coordinates":{"lat":50.260787,"lng":19.014292}},{"name":"Katowice Plac Wolności-4.2⭐️","coordinates":{"lat":50.26039290000001,"lng":19.0127867}},{"name":"Katowice Sobieskiego-3.7⭐️","coordinates":{"lat":50.26034500000001,"lng":19.011899}},{"name":"Katowice Sobieskiego-⭐️","coordinates":{"lat":50.2603296,"lng":19.0118395}},{"name":"Katowice Sobieskiego-4.3⭐️","coordinates":{"lat":50.26029,"lng":19.01185}}]}
